fastapi_paginate/__init__.py
fastapi_paginate/api.py
fastapi_paginate/bases.py
fastapi_paginate/default.py
fastapi_paginate/ext/__init__.py
fastapi_paginate/ext/async_sqlalchemy.py
fastapi_paginate/ext/async_sqlmodel.py
fastapi_paginate/ext/asyncpg.py
fastapi_paginate/ext/databases.py
fastapi_paginate/ext/django.py
fastapi_paginate/ext/gino.py
fastapi_paginate/ext/mongoengine.py
fastapi_paginate/ext/motor.py
fastapi_paginate/ext/orm.py
fastapi_paginate/ext/ormar.py
fastapi_paginate/ext/piccolo.py
fastapi_paginate/ext/py.typed
fastapi_paginate/ext/sqlalchemy.py
fastapi_paginate/ext/sqlalchemy_future.py
fastapi_paginate/ext/sqlmodel.py
fastapi_paginate/ext/tortoise.py
fastapi_paginate/paginator.py
fastapi_paginate/py.typed
fastapi_paginate-0.1.0.dist-info/LICENSE
fastapi_paginate-0.1.0.dist-info/WHEEL
fastapi_paginate-0.1.0.dist-info/METADATA
fastapi_paginate-0.1.0.dist-info/RECORD
